{"polyp": 0, "ulcerative-colitis-grade-2": 1, "cecum": 2, "bbps-2-3": 3, "esophagitis-b-d": 4, "instrument": 5, "dyed-lifted-polyps": 6, "dyed-resection-margins": 7, "bbps-0-1": 8, "pylorus": 9, "retroflex-rectum": 10, "z-line": 11, "esophagitis-a": 12, "retroflex-stomach": 13, "barretts-short-segment": 14, "impacted-stool": 15, "ulcerative-colitis-grade-1": 16, "ulcerative-colitis-grade-3": 17, "barretts": 18, "ulcerative-colitis-grade-2-3": 19, "ulcerative-colitis-grade-0-1": 20, "ulcerative-colitis-grade-1-2": 21, "hemorrhoids": 22, "ileum": 23}